pyrolog/__init__.py
pyrolog/_types.py
pyrolog/colors.py
pyrolog/defaults.py
pyrolog/empty_colors.py
pyrolog/formatters.py
pyrolog/group.py
pyrolog/handlers.py
pyrolog/logger.py
pyrolog/logging_context.py
pyrolog/utils.py
pyrolog/version.py
pyrolog-2.3.0.dist-info/LICENSE
pyrolog-2.3.0.dist-info/METADATA
pyrolog-2.3.0.dist-info/WHEEL
pyrolog-2.3.0.dist-info/top_level.txt
pyrolog-2.3.0.dist-info/RECORD
