Metadata-Version: 2.1
Name: pyrolog
Version: 2.3.0
Summary: Pretty modern colored logging library
Author-email: ftdot <ftdoot@gmail.com>
License: GNU LESSER GENERAL PUBLIC LICENSE
Project-URL: Homepage, https://github.com/ftdot/pyrolog
Keywords: journal,colored,modern,pretty,color,library,logging,logger,logs
Classifier: Environment :: Plugins
Classifier: License :: OSI Approved :: GNU Lesser General Public License v2 or later (LGPLv2+)
Classifier: License :: OSI Approved :: GNU Library or Lesser General Public License (LGPL)
Classifier: Programming Language :: Python
Classifier: Programming Language :: Python :: 3
Classifier: Programming Language :: Python :: 3.9
Classifier: Programming Language :: Python :: 3.10
Classifier: Topic :: Documentation :: Sphinx
Classifier: Topic :: System :: Logging
Requires-Python: >=3.9
License-File: LICENSE
Requires-Dist: colorama
Provides-Extra: docs
Requires-Dist: sphinx ; extra == 'docs'
Requires-Dist: furo ; extra == 'docs'
